ad_pipeline/__init__.py
ad_pipeline/common.py
ad_pipeline/constants.py
ad_pipeline/futures/__init__.py
ad_pipeline/futures/service.py
ad_pipeline/spot/__init__.py
ad_pipeline/spot/service.py
ad_pipeline-0.1.21.dist-info/LICENSE
ad_pipeline-0.1.21.dist-info/METADATA
ad_pipeline-0.1.21.dist-info/WHEEL
ad_pipeline-0.1.21.dist-info/top_level.txt
ad_pipeline-0.1.21.dist-info/RECORD
