Metadata-Version: 2.1
Name: ad_pipeline
Version: 0.1.21
Summary: AD Pipeline Beta
Author: technology@firestorm.capital.com
License-File: LICENSE
